[{ "model": "events.country", "pk":1,"fields": { "name": "Австралия", "name_en": "Australia", "image": "" } },
{ "model": "events.country", "pk":2,"fields": { "name": "Австралия и Океания", "name_en": "Australia and Oceania", "image": "" } },
{ "model": "events.country", "pk":3,"fields": { "name": "Австрия", "name_en": "Austria", "image": "" } },
{ "model": "events.country", "pk":4,"fields": { "name": "Азербайджан", "name_en": "Azerbaijan", "image": "" } },
{ "model": "events.country", "pk":5,"fields": { "name": "Азия", "name_en": "Asia", "image": "" } },
{ "model": "events.country", "pk":6,"fields": { "name": "Албания", "name_en": "Albania", "image": "" } },
{ "model": "events.country", "pk":7,"fields": { "name": "Алжир", "name_en": "Algeria", "image": "" } },
{ "model": "events.country", "pk":8,"fields": { "name": "Англия", "name_en": "England", "image": "" } },
{ "model": "events.country", "pk":9,"fields": { "name": "Ангола", "name_en": "Angola", "image": "" } },
{ "model": "events.country", "pk":10,"fields": { "name": "Андорра", "name_en": "Andorra", "image": "" } },
{ "model": "events.country", "pk":11,"fields": { "name": "Антигуа и Барбуда", "name_en": "Antigua and Barbuda", "image": "" } },
{ "model": "events.country", "pk":12,"fields": { "name": "Аргентина", "name_en": "Argentina", "image": "" } },
{ "model": "events.country", "pk":13,"fields": { "name": "Армения", "name_en": "Armenia", "image": "" } },
{ "model": "events.country", "pk":14,"fields": { "name": "Аруба", "name_en": "Aruba", "image": "" } },
{ "model": "events.country", "pk":15,"fields": { "name": "Африка", "name_en": "Africa", "image": "" } },
{ "model": "events.country", "pk":16,"fields": { "name": "Бангладеш", "name_en": "Bangladesh", "image": "" } },
{ "model": "events.country", "pk":17,"fields": { "name": "Бахрейн", "name_en": "Bahrain", "image": "" } },
{ "model": "events.country", "pk":18,"fields": { "name": "Беларусь", "name_en": "Belarus", "image": "" } },
{ "model": "events.country", "pk":19,"fields": { "name": "Бельгия", "name_en": "Belgium", "image": "" } },
{ "model": "events.country", "pk":20,"fields": { "name": "Бенин", "name_en": "Benin", "image": "" } },
{ "model": "events.country", "pk":21,"fields": { "name": "Бермуды", "name_en": "Bermuda", "image": "" } },
{ "model": "events.country", "pk":22,"fields": { "name": "Болгария", "name_en": "Bulgaria", "image": "" } },
{ "model": "events.country", "pk":23,"fields": { "name": "Боливия", "name_en": "Bolivia", "image": "" } },
{ "model": "events.country", "pk":24,"fields": { "name": "Босния и Герцеговина", "name_en": "Bosnia and Herzegovina", "image": "" } },
{ "model": "events.country", "pk":25,"fields": { "name": "Ботсвана", "name_en": "Botswana", "image": "" } },
{ "model": "events.country", "pk":26,"fields": { "name": "Бразилия", "name_en": "Brazil", "image": "" } },
{ "model": "events.country", "pk":27,"fields": { "name": "Буркина-Фасо", "name_en": "Burkina Faso", "image": "" } },
{ "model": "events.country", "pk":28,"fields": { "name": "Бурунди", "name_en": "Burundi", "image": "" } },
{ "model": "events.country", "pk":29,"fields": { "name": "Бутан", "name_en": "Bhutan", "image": "" } },
{ "model": "events.country", "pk":30,"fields": { "name": "Венгрия", "name_en": "Hungary", "image": "" } },
{ "model": "events.country", "pk":31,"fields": { "name": "Венесуэла", "name_en": "Venezuela", "image": "" } },
{ "model": "events.country", "pk":32,"fields": { "name": "Вьетнам", "name_en": "Vietnam", "image": "" } },
{ "model": "events.country", "pk":33,"fields": { "name": "Габон", "name_en": "Gabon", "image": "" } },
{ "model": "events.country", "pk":34,"fields": { "name": "Гаити", "name_en": "Haiti", "image": "" } },
{ "model": "events.country", "pk":35,"fields": { "name": "Гамбия", "name_en": "Gambia", "image": "" } },
{ "model": "events.country", "pk":36,"fields": { "name": "Гана", "name_en": "Ghana", "image": "" } },
{ "model": "events.country", "pk":37,"fields": { "name": "Гватемала", "name_en": "Guatemala", "image": "" } },
{ "model": "events.country", "pk":38,"fields": { "name": "Гвинея", "name_en": "Guinea", "image": "" } },
{ "model": "events.country", "pk":39,"fields": { "name": "Германия", "name_en": "Germany", "image": "" } },
{ "model": "events.country", "pk":40,"fields": { "name": "Гибралтар", "name_en": "Gibraltar", "image": "" } },
{ "model": "events.country", "pk":41,"fields": { "name": "Гондурас", "name_en": "Honduras", "image": "" } },
{ "model": "events.country", "pk":42,"fields": { "name": "Гонконг", "name_en": "Hong Kong", "image": "" } },
{ "model": "events.country", "pk":43,"fields": { "name": "Гренада", "name_en": "Grenada", "image": "" } },
{ "model": "events.country", "pk":44,"fields": { "name": "Греция", "name_en": "Greece", "image": "" } },
{ "model": "events.country", "pk":45,"fields": { "name": "Грузия", "name_en": "Georgia", "image": "" } },
{ "model": "events.country", "pk":46,"fields": { "name": "Дания", "name_en": "Denmark", "image": "" } },
{ "model": "events.country", "pk":47,"fields": { "name": "Джибути", "name_en": "Djibouti", "image": "" } },
{ "model": "events.country", "pk":48,"fields": { "name": "Доминиканская Республика", "name_en": "The Dominican Republic", "image": "" } },
{ "model": "events.country", "pk":49,"fields": { "name": "Европа", "name_en": "Europe", "image": "" } },
{ "model": "events.country", "pk":50,"fields": { "name": "Египет", "name_en": "Egypt", "image": "" } },
{ "model": "events.country", "pk":51,"fields": { "name": "Замбия", "name_en": "Zambia", "image": "" } },
{ "model": "events.country", "pk":52,"fields": { "name": "Зимбабве", "name_en": "Zimbabwe", "image": "" } },
{ "model": "events.country", "pk":53,"fields": { "name": "Израиль", "name_en": "Israel", "image": "" } },
{ "model": "events.country", "pk":54,"fields": { "name": "Индия", "name_en": "India", "image": "" } },
{ "model": "events.country", "pk":55,"fields": { "name": "Индонезия", "name_en": "Indonesia", "image": "" } },
{ "model": "events.country", "pk":56,"fields": { "name": "Иордания", "name_en": "Jordan", "image": "" } },
{ "model": "events.country", "pk":57,"fields": { "name": "Ирак", "name_en": "Iraq", "image": "" } },
{ "model": "events.country", "pk":58,"fields": { "name": "Иран", "name_en": "Iran", "image": "" } },
{ "model": "events.country", "pk":59,"fields": { "name": "Ирландия", "name_en": "Irish", "image": "" } },
{ "model": "events.country", "pk":60,"fields": { "name": "Исландия", "name_en": "Iceland", "image": "" } },
{ "model": "events.country", "pk":61,"fields": { "name": "Испания", "name_en": "Spain", "image": "" } },
{ "model": "events.country", "pk":62,"fields": { "name": "Италия", "name_en": "Italy", "image": "" } },
{ "model": "events.country", "pk":63,"fields": { "name": "Йемен", "name_en": "Yemen", "image": "" } },
{ "model": "events.country", "pk":64,"fields": { "name": "Кабо-Верде", "name_en": "Cape Verde", "image": "" } },
{ "model": "events.country", "pk":65,"fields": { "name": "Казахстан", "name_en": "Kazakhstan", "image": "" } },
{ "model": "events.country", "pk":66,"fields": { "name": "Камбоджа", "name_en": "Cambodia", "image": "" } },
{ "model": "events.country", "pk":67,"fields": { "name": "Камерун", "name_en": "Cameroon", "image": "" } },
{ "model": "events.country", "pk":68,"fields": { "name": "Канада", "name_en": "Canada", "image": "" } },
{ "model": "events.country", "pk":69,"fields": { "name": "Катар", "name_en": "Qatar", "image": "" } },
{ "model": "events.country", "pk":70,"fields": { "name": "Кения", "name_en": "Kenya", "image": "" } },
{ "model": "events.country", "pk":71,"fields": { "name": "Кипр", "name_en": "Cyprus", "image": "" } },
{ "model": "events.country", "pk":72,"fields": { "name": "Китай", "name_en": "China", "image": "" } },
{ "model": "events.country", "pk":73,"fields": { "name": "Колумбия", "name_en": "Colombia", "image": "" } },
{ "model": "events.country", "pk":74,"fields": { "name": "Конго", "name_en": "Congo", "image": "" } },
{ "model": "events.country", "pk":75,"fields": { "name": "Конго ДР", "name_en": "Congo DR", "image": "" } },
{ "model": "events.country", "pk":76,"fields": { "name": "Косово", "name_en": "Kosovo", "image": "" } },
{ "model": "events.country", "pk":77,"fields": { "name": "Коста-Рика", "name_en": "Costa Rica", "image": "" } },
{ "model": "events.country", "pk":78,"fields": { "name": "Кот-д'Ивуар", "name_en": "Ivory Coast", "image": "" } },
{ "model": "events.country", "pk":79,"fields": { "name": "Куба", "name_en": "Cuba", "image": "" } },
{ "model": "events.country", "pk":80,"fields": { "name": "Кувейт", "name_en": "Kuwait", "image": "" } },
{ "model": "events.country", "pk":81,"fields": { "name": "Кыргызстан", "name_en": "Kyrgyzstan", "image": "" } },
{ "model": "events.country", "pk":82,"fields": { "name": "Кюрасао", "name_en": "Curacao", "image": "" } },
{ "model": "events.country", "pk":83,"fields": { "name": "Лаос", "name_en": "Laos", "image": "" } },
{ "model": "events.country", "pk":84,"fields": { "name": "Латвия", "name_en": "Latvia", "image": "" } },
{ "model": "events.country", "pk":85,"fields": { "name": "Лесото", "name_en": "Lesotho", "image": "" } },
{ "model": "events.country", "pk":86,"fields": { "name": "Либерия", "name_en": "Liberia", "image": "" } },
{ "model": "events.country", "pk":87,"fields": { "name": "Ливан", "name_en": "Lebanon", "image": "" } },
{ "model": "events.country", "pk":88,"fields": { "name": "Ливия", "name_en": "Libya", "image": "" } },
{ "model": "events.country", "pk":89,"fields": { "name": "Литва", "name_en": "Lithuania", "image": "" } },
{ "model": "events.country", "pk":90,"fields": { "name": "Лихтенштейн", "name_en": "Liechtenstein", "image": "" } },
{ "model": "events.country", "pk":91,"fields": { "name": "Люксембург", "name_en": "Luxembourg", "image": "" } },
{ "model": "events.country", "pk":92,"fields": { "name": "Маврикий", "name_en": "Mauritius", "image": "" } },
{ "model": "events.country", "pk":93,"fields": { "name": "Мавритания", "name_en": "Mauritania", "image": "" } },
{ "model": "events.country", "pk":94,"fields": { "name": "Макао", "name_en": "Macau", "image": "" } },
{ "model": "events.country", "pk":95,"fields": { "name": "Малави", "name_en": "Malawi", "image": "" } },
{ "model": "events.country", "pk":96,"fields": { "name": "Малайзия", "name_en": "Malaysia", "image": "" } },
{ "model": "events.country", "pk":97,"fields": { "name": "Мали", "name_en": "Mali", "image": "" } },
{ "model": "events.country", "pk":98,"fields": { "name": "Мальдивы", "name_en": "Maldives", "image": "" } },
{ "model": "events.country", "pk":99,"fields": { "name": "Мальта", "name_en": "Malta", "image": "" } },
{ "model": "events.country", "pk":100,"fields": { "name": "Марокко", "name_en": "Morocco", "image": "" } },
{ "model": "events.country", "pk":101,"fields": { "name": "Мексика", "name_en": "Mexico", "image": "" } },
{ "model": "events.country", "pk":102,"fields": { "name": "Мир", "name_en": "World", "image": "" } },
{ "model": "events.country", "pk":103,"fields": { "name": "Мозамбик", "name_en": "Mozambique", "image": "" } },
{ "model": "events.country", "pk":104,"fields": { "name": "Молдова", "name_en": "Moldova", "image": "" } },
{ "model": "events.country", "pk":105,"fields": { "name": "Монголия", "name_en": "Mongolia", "image": "" } },
{ "model": "events.country", "pk":106,"fields": { "name": "Мьянма", "name_en": "Myanmar", "image": "" } },
{ "model": "events.country", "pk":107,"fields": { "name": "Намибия", "name_en": "Namibia", "image": "" } },
{ "model": "events.country", "pk":108,"fields": { "name": "Нигер", "name_en": "Niger", "image": "" } },
{ "model": "events.country", "pk":109,"fields": { "name": "Нигерия", "name_en": "Nigeria", "image": "" } },
{ "model": "events.country", "pk":110,"fields": { "name": "Нидерланды", "name_en": "Netherlands", "image": "" } },
{ "model": "events.country", "pk":111,"fields": { "name": "Никарагуа", "name_en": "Nicaragua", "image": "" } },
{ "model": "events.country", "pk":112,"fields": { "name": "Новая Зеландия", "name_en": "New Zealand", "image": "" } },
{ "model": "events.country", "pk":113,"fields": { "name": "Норвегия", "name_en": "Norway", "image": "" } },
{ "model": "events.country", "pk":114,"fields": { "name": "ОАЭ", "name_en": "UAE", "image": "" } },
{ "model": "events.country", "pk":115,"fields": { "name": "Оман", "name_en": "Oman", "image": "" } },
{ "model": "events.country", "pk":116,"fields": { "name": "Пакистан", "name_en": "Pakistan", "image": "" } },
{ "model": "events.country", "pk":117,"fields": { "name": "Палестина", "name_en": "Palestine", "image": "" } },
{ "model": "events.country", "pk":118,"fields": { "name": "Панама", "name_en": "Panama hat", "image": "" } },
{ "model": "events.country", "pk":119,"fields": { "name": "Парагвай", "name_en": "Paraguay", "image": "" } },
{ "model": "events.country", "pk":120,"fields": { "name": "Перу", "name_en": "Peru", "image": "" } },
{ "model": "events.country", "pk":121,"fields": { "name": "Польша", "name_en": "Poland", "image": "" } },
{ "model": "events.country", "pk":122,"fields": { "name": "Португалия", "name_en": "Portugal", "image": "" } },
{ "model": "events.country", "pk":123,"fields": { "name": "Реюньон", "name_en": "Reunion", "image": "" } },
{ "model": "events.country", "pk":124,"fields": { "name": "Руанда", "name_en": "Rwanda", "image": "" } },
{ "model": "events.country", "pk":125,"fields": { "name": "Румыния", "name_en": "Romania", "image": "" } },
{ "model": "events.country", "pk":126,"fields": { "name": "Сальвадор", "name_en": "El Salvador", "image": "" } },
{ "model": "events.country", "pk":127,"fields": { "name": "Сан-Марино", "name_en": "San Marino", "image": "" } },
{ "model": "events.country", "pk":128,"fields": { "name": "Саудовская Аравия", "name_en": "Saudi Arabia", "image": "" } },
{ "model": "events.country", "pk":129,"fields": { "name": "Северная Ирландия", "name_en": "Northern Ireland", "image": "" } },
{ "model": "events.country", "pk":130,"fields": { "name": "Северная и Центральная Америка", "name_en": "North and Central America", "image": "" } },
{ "model": "events.country", "pk":131,"fields": { "name": "Северная Македония", "name_en": "Northern Macedonia", "image": "" } },
{ "model": "events.country", "pk":132,"fields": { "name": "Сейшельские острова", "name_en": "Seychelles", "image": "" } },
{ "model": "events.country", "pk":133,"fields": { "name": "Сенегал", "name_en": "Senegal", "image": "" } },
{ "model": "events.country", "pk":134,"fields": { "name": "Сербия", "name_en": "Serbia", "image": "" } },
{ "model": "events.country", "pk":135,"fields": { "name": "Сербия и Черногория", "name_en": "Serbia and Montenegro", "image": "" } },
{ "model": "events.country", "pk":136,"fields": { "name": "Сингапур", "name_en": "Singapore", "image": "" } },
{ "model": "events.country", "pk":137,"fields": { "name": "Сирия", "name_en": "Syria", "image": "" } },
{ "model": "events.country", "pk":138,"fields": { "name": "Словакия", "name_en": "Slovakia", "image": "" } },
{ "model": "events.country", "pk":139,"fields": { "name": "Словения", "name_en": "Slovenia", "image": "" } },
{ "model": "events.country", "pk":140,"fields": { "name": "Сомали", "name_en": "Somalia", "image": "" } },
{ "model": "events.country", "pk":141,"fields": { "name": "Судан", "name_en": "Sudan", "image": "" } },
{ "model": "events.country", "pk":142,"fields": { "name": "США", "name_en": "USA", "image": "" } },
{ "model": "events.country", "pk":143,"fields": { "name": "Сьерра-Леоне", "name_en": "Sierra Leone", "image": "" } },
{ "model": "events.country", "pk":144,"fields": { "name": "Таджикистан", "name_en": "Tadjikistan", "image": "" } },
{ "model": "events.country", "pk":145,"fields": { "name": "Таиланд", "name_en": "Thailand", "image": "" } },
{ "model": "events.country", "pk":146,"fields": { "name": "Тайвань", "name_en": "Taiwan", "image": "" } },
{ "model": "events.country", "pk":147,"fields": { "name": "Танзания", "name_en": "Tanzania", "image": "" } },
{ "model": "events.country", "pk":148,"fields": { "name": "Того", "name_en": "That", "image": "" } },
{ "model": "events.country", "pk":149,"fields": { "name": "Тринидад и Тобаго", "name_en": "Trinidad and Tobago", "image": "" } },
{ "model": "events.country", "pk":150,"fields": { "name": "Тунис", "name_en": "Tunisia", "image": "" } },
{ "model": "events.country", "pk":151,"fields": { "name": "Туркменистан", "name_en": "Turkmenistan", "image": "" } },
{ "model": "events.country", "pk":152,"fields": { "name": "Турция", "name_en": "Turkey", "image": "" } },
{ "model": "events.country", "pk":153,"fields": { "name": "Уганда", "name_en": "Uganda", "image": "" } },
{ "model": "events.country", "pk":154,"fields": { "name": "Узбекистан", "name_en": "Uzbekistan", "image": "" } },
{ "model": "events.country", "pk":155,"fields": { "name": "Украина", "name_en": "Ukraine", "image": "" } },
{ "model": "events.country", "pk":156,"fields": { "name": "Уругвай", "name_en": "Uruguay", "image": "" } },
{ "model": "events.country", "pk":157,"fields": { "name": "Уэльс", "name_en": "Wales", "image": "" } },
{ "model": "events.country", "pk":158,"fields": { "name": "Фарерские острова", "name_en": "Faroe Islands", "image": "" } },
{ "model": "events.country", "pk":159,"fields": { "name": "Фиджи", "name_en": "Fiji", "image": "" } },
{ "model": "events.country", "pk":160,"fields": { "name": "Филиппины", "name_en": "Philippines", "image": "" } },
{ "model": "events.country", "pk":161,"fields": { "name": "Финляндия", "name_en": "Finland", "image": "" } },
{ "model": "events.country", "pk":162,"fields": { "name": "Франция", "name_en": "France", "image": "" } },
{ "model": "events.country", "pk":163,"fields": { "name": "Хорватия", "name_en": "Croatia", "image": "" } },
{ "model": "events.country", "pk":164,"fields": { "name": "Черногория", "name_en": "Montenegro", "image": "" } },
{ "model": "events.country", "pk":165,"fields": { "name": "Чехия", "name_en": "Czech", "image": "" } },
{ "model": "events.country", "pk":166,"fields": { "name": "Чили", "name_en": "Chile", "image": "" } },
{ "model": "events.country", "pk":167,"fields": { "name": "Швейцария", "name_en": "Switzerland", "image": "" } },
{ "model": "events.country", "pk":168,"fields": { "name": "Швеция", "name_en": "Sweden", "image": "" } },
{ "model": "events.country", "pk":169,"fields": { "name": "Шотландия", "name_en": "Scotland", "image": "" } },
{ "model": "events.country", "pk":170,"fields": { "name": "Шри-Ланка", "name_en": "Sri Lanka", "image": "" } },
{ "model": "events.country", "pk":171,"fields": { "name": "Эквадор", "name_en": "Ecuador", "image": "" } },
{ "model": "events.country", "pk":172,"fields": { "name": "Эсватини", "name_en": "Eswatini", "image": "" } },
{ "model": "events.country", "pk":173,"fields": { "name": "Эстония", "name_en": "Estonia", "image": "" } },
{ "model": "events.country", "pk":174,"fields": { "name": "Эфиопия", "name_en": "Ethiopia", "image": "" } },
{ "model": "events.country", "pk":175,"fields": { "name": "Южная Америка", "name_en": "South America", "image": "" } },
{ "model": "events.country", "pk":176,"fields": { "name": "Южная Африка", "name_en": "South Africa", "image": "" } },
{ "model": "events.country", "pk":177,"fields": { "name": "Южная Корея", "name_en": "South Korea", "image": "" } },
{ "model": "events.country", "pk":178,"fields": { "name": "Ямайка", "name_en": "Jamaica", "image": "" } },
{ "model": "events.country", "pk":179,"fields": { "name": "Япония", "name_en": "Japan", "image": "" } },
{ "model": "events.country", "pk":180,"fields": { "name": "Великобритания", "name_en": "Great Britain", "image": "" } },
{ "model": "events.country", "pk":181,"fields": { "name": "Гваделупа", "name_en": "Guadeloupe", "image": "" } },
{ "model": "events.country", "pk":182,"fields": { "name": "Гуам", "name_en": "Guam", "image": "" } },
{ "model": "events.country", "pk":183,"fields": { "name": "Мартиника", "name_en": "Martinique", "image": "" } },
{ "model": "events.country", "pk":184,"fields": { "name": "Монако", "name_en": "Monaco", "image": "" } },
{ "model": "events.country", "pk":185,"fields": { "name": "Новая Каледония", "name_en": "New Caledonia", "image": "" } },
{ "model": "events.country", "pk":186,"fields": { "name": "Пуэрто-Рико", "name_en": "Puerto Rico", "image": "" } },
{ "model": "events.country", "pk":187,"fields": { "name": "Россия", "name_en": "Russia", "image": "" } },
{ "model": "events.country", "pk":188,"fields": { "name": "Афганистан", "name_en": "Afghanistan", "image": "" } },
{ "model": "events.country", "pk":189,"fields": { "name": "Вануату", "name_en": "Vanuatu", "image": "" } },
{ "model": "events.country", "pk":190,"fields": { "name": "Сент-Винсент и Гренадины", "name_en": "Saint Vincent and the Grenadines", "image": "" } },
{ "model": "events.country", "pk":191,"fields": { "name": "Северная Корея", "name_en": "North Korea", "image": "" } },
{ "model": "events.country", "pk":192,"fields": { "name": "СНГ", "name_en": "CIS", "image": "" } },
{ "model": "events.country", "pk":193,"fields": { "name": "Юго-восточная Азия", "name_en": "Southeast Asia", "image": "" } },
{ "model": "events.country", "pk":194,"fields": { "name": "Барбадос", "name_en": "Barbados", "image": "" } },
{ "model": "events.country", "pk":195,"fields": { "name": "Чад", "name_en": "Chad", "image": "" } },
{ "model": "events.country", "pk":196,"fields": { "name": "Объединенные Арабские Эмираты", "name_en": "United Arab Emirates", "image": "" } },
{ "model": "events.country", "pk":197,"fields": { "name": "Ангилья", "name_en": "Anguilla", "image": "" } },
{ "model": "events.country", "pk":198,"fields": { "name": "Антарктика", "name_en": "Antarctic region", "image": "" } },
{ "model": "events.country", "pk":199,"fields": { "name": "Американское Самоа", "name_en": "American Samoa", "image": "" } },
{ "model": "events.country", "pk":200,"fields": { "name": "Аландские острова", "name_en": "The Aland Islands", "image": "" } },
{ "model": "events.country", "pk":201,"fields": { "name": "Сен-Бартелеми", "name_en": "Saint Barthelemy", "image": "" } },
{ "model": "events.country", "pk":202,"fields": { "name": "Бруней", "name_en": "Brunei", "image": "" } },
{ "model": "events.country", "pk":203,"fields": { "name": "Бонэйр, Синт-Эстатиус и Саба", "name_en": "Bonaire, Sint Eustatius and Saba", "image": "" } },
{ "model": "events.country", "pk":204,"fields": { "name": "Жемчужина", "name_en": "Pearl", "image": "" } },
{ "model": "events.country", "pk":205,"fields": { "name": "Босния и Герсеговина", "name_en": "Bosnia and Herzegovina", "image": "" } },
{ "model": "events.country", "pk":206,"fields": { "name": "Утолженное", "name_en": "Thickened", "image": "" } },
{ "model": "events.country", "pk":207,"fields": { "name": "Гамбий", "name_en": "Gambia", "image": "" } }]
